{
	"name": "TransformedWeatherMetrics",
	"properties": {
		"type": "WranglingDataFlow",
		"typeProperties": {
			"sources": [
				{
					"name": "WeatherMetrics",
					"script": "source(allowSchemaDrift: true,\n\tvalidateSchema: false,\n\tignoreNoFilesFound: false) ~>  WeatherMetrics",
					"dataset": {
						"referenceName": "WeatherMetrics",
						"type": "DatasetReference"
					}
				}
			],
			"script": "section Section1;\r\nshared WeatherMetrics = let AdfDoc = AzureStorage.BlobContents(\"https://sefdinenassufblobcontain.blob.core.windows.net/input/weathermetrics-6506f85ed6fa8029696523.csv\"),Csv = Csv.Document(AdfDoc, [Delimiter = \",\", Encoding = TextEncoding.Utf8, QuoteStyle = QuoteStyle.Csv]), PromotedHeaders = Table.PromoteHeaders(Csv, [PromoteAllScalars = true]) in  PromotedHeaders;\r\nshared UserQuery = let Source = #\"WeatherMetrics\",\r\n  #\"Changed column type\" = Table.TransformColumnTypes(Source, {{\"DateID\", Int64.Type}, {\"RegionID\", Int64.Type}, {\"AverageTemperature\", Int64.Type}, {\"Humidity\", Int64.Type}, {\"WindSpeed\", Int64.Type}, {\"Rainfall\", Int64.Type}, {\"SunshineHours\", Int64.Type}}) in #\"Changed column type\";\r\n",
			"documentLocale": "en-us"
		}
	}
}